storeify/__init__.py
storeify/base.py
storeify/errors.py
storeify/file.py
storeify/memory.py
storeify/shared.py
storeify/utils.py
storeify-0.2.1.dist-info/LICENSE
storeify-0.2.1.dist-info/WHEEL
storeify-0.2.1.dist-info/METADATA
storeify-0.2.1.dist-info/RECORD
